{"id":"760405d2-be1b-478f-9002-9ec19f2fcd75","title":"Tmux","desc":"","updated":1609924438892,"created":1609924416641,"custom":{},"fname":"cli.tmux","type":"note","vault":{"fsPath":".","name":"vault","selfContained":true},"contentHash":"ca03b9cccb82cb7a052cc937ff19148b","links":[],"anchors":{"tmux":{"type":"header","text":"Tmux","value":"tmux","line":8,"column":0,"depth":1},"enable-ctrl-keys-temp":{"type":"header","text":"Enable CTRL keys temp","value":"enable-ctrl-keys-temp","line":10,"column":0,"depth":2}},"children":[],"parent":"132fe0fe-fc74-4dbe-982a-9dcac677f664","data":{},"schema":{"schemaId":"cli","moduleId":"cli"}}
